{"directed": false, "multigraph": false, "graph": {}, "nodes": [{"id": "Thing"}, {"id": "CheeseyPizza"}, {"id": "Country"}, {"id": "DomainConcept"}, {"id": "Food"}, {"id": "Pizza"}, {"id": "NamedPizza"}, {"id": "American"}, {"id": "AmericanHot"}, {"id": "Cajun"}, {"id": "Capricciosa"}, {"id": "Caprina"}, {"id": "Fiorentina"}, {"id": "FourSeasons"}, {"id": "FruttiDiMare"}, {"id": "Giardiniera"}, {"id": "LaReine"}, {"id": "Margherita"}, {"id": "Mushroom"}, {"id": "Napoletana"}, {"id": "Parmense"}, {"id": "PolloAdAstra"}, {"id": "PrinceCarlo"}, {"id": "QuattroFormaggi"}, {"id": "Rosa"}, {"id": "Siciliana"}, {"id": "SloppyGiuseppe"}, {"id": "Soho"}, {"id": "Veneziana"}, {"id": "UnclosedPizza"}, {"id": "PizzaBase"}, {"id": "DeepPanBase"}, {"id": "ThinAndCrispyBase"}, {"id": "PizzaTopping"}, {"id": "FishTopping"}, {"id": "AnchoviesTopping"}, {"id": "PrawnsTopping"}, {"id": "MixedSeafoodTopping"}, {"id": "VegetableTopping"}, {"id": "TomatoTopping"}, {"id": "SundriedTomatoTopping"}, {"id": "SlicedTomatoTopping"}, {"id": "ArtichokeTopping"}, {"id": "AsparagusTopping"}, {"id": "OnionTopping"}, {"id": "RedOnionTopping"}, {"id": "CaperTopping"}, {"id": "OliveTopping"}, {"id": "CheeseyVegetableTopping"}, {"id": "GarlicTopping"}, {"id": "SpinachTopping"}, {"id": "MushroomTopping"}, {"id": "LeekTopping"}, {"id": "PetitPoisTopping"}, {"id": "PepperTopping"}, {"id": "JalapenoPepperTopping"}, {"id": "PeperonataTopping"}, {"id": "GreenPepperTopping"}, {"id": "HotGreenPepperTopping"}, {"id": "SweetPepperTopping"}, {"id": "RocketTopping"}, {"id": "HerbSpiceTopping"}, {"id": "CajunSpiceTopping"}, {"id": "RosemaryTopping"}, {"id": "CheeseTopping"}, {"id": "MozzarellaTopping"}, {"id": "GoatsCheeseTopping"}, {"id": "ParmesanTopping"}, {"id": "FourCheesesTopping"}, {"id": "GorgonzolaTopping"}, {"id": "MeatTopping"}, {"id": "PeperoniSausageTopping"}, {"id": "HamTopping"}, {"id": "ParmaHamTopping"}, {"id": "ChickenTopping"}, {"id": "HotSpicedBeefTopping"}, {"id": "FruitTopping"}, {"id": "SultanaTopping"}, {"id": "NutTopping"}, {"id": "PineKernels"}, {"id": "SauceTopping"}, {"id": "TobascoPepperSauce"}, {"id": "IceCream"}, {"id": "ValuePartition"}, {"id": "Spiciness"}, {"id": "Mild"}, {"id": "Hot"}, {"id": "Medium"}, {"id": "InterestingPizza"}, {"id": "MeatyPizza"}, {"id": "NonVegetarianPizza"}, {"id": "VegetarianPizza"}, {"id": "RealItalianPizza"}, {"id": "SpicyPizza"}, {"id": "SpicyTopping"}, {"id": "SpicyPizzaEquivalent"}, {"id": "ThinAndCrispyPizza"}, {"id": "VegetarianPizzaEquivalent1"}, {"id": "VegetarianTopping"}, {"id": "VegetarianPizzaEquivalent2"}], "links": [{"source": "Thing", "target": "CheeseyPizza"}, {"source": "Thing", "target": "Country"}, {"source": "Thing", "target": "DomainConcept"}, {"source": "Thing", "target": "ValuePartition"}, {"source": "Thing", "target": "InterestingPizza"}, {"source": "Thing", "target": "MeatyPizza"}, {"source": "Thing", "target": "NonVegetarianPizza"}, {"source": "Thing", "target": "VegetarianPizza"}, {"source": "Thing", "target": "RealItalianPizza"}, {"source": "Thing", "target": "SpicyPizza"}, {"source": "Thing", "target": "SpicyTopping"}, {"source": "Thing", "target": "SpicyPizzaEquivalent"}, {"source": "Thing", "target": "ThinAndCrispyPizza"}, {"source": "Thing", "target": "VegetarianPizzaEquivalent1"}, {"source": "Thing", "target": "VegetarianTopping"}, {"source": "Thing", "target": "VegetarianPizzaEquivalent2"}, {"source": "DomainConcept", "target": "Food"}, {"source": "Food", "target": "Pizza"}, {"source": "Food", "target": "PizzaBase"}, {"source": "Food", "target": "PizzaTopping"}, {"source": "Food", "target": "IceCream"}, {"source": "Pizza", "target": "NamedPizza"}, {"source": "Pizza", "target": "UnclosedPizza"}, {"source": "NamedPizza", "target": "American"}, {"source": "NamedPizza", "target": "AmericanHot"}, {"source": "NamedPizza", "target": "Cajun"}, {"source": "NamedPizza", "target": "Capricciosa"}, {"source": "NamedPizza", "target": "Caprina"}, {"source": "NamedPizza", "target": "Fiorentina"}, {"source": "NamedPizza", "target": "FourSeasons"}, {"source": "NamedPizza", "target": "FruttiDiMare"}, {"source": "NamedPizza", "target": "Giardiniera"}, {"source": "NamedPizza", "target": "LaReine"}, {"source": "NamedPizza", "target": "Margherita"}, {"source": "NamedPizza", "target": "Mushroom"}, {"source": "NamedPizza", "target": "Napoletana"}, {"source": "NamedPizza", "target": "Parmense"}, {"source": "NamedPizza", "target": "PolloAdAstra"}, {"source": "NamedPizza", "target": "PrinceCarlo"}, {"source": "NamedPizza", "target": "QuattroFormaggi"}, {"source": "NamedPizza", "target": "Rosa"}, {"source": "NamedPizza", "target": "Siciliana"}, {"source": "NamedPizza", "target": "SloppyGiuseppe"}, {"source": "NamedPizza", "target": "Soho"}, {"source": "NamedPizza", "target": "Veneziana"}, {"source": "PizzaBase", "target": "DeepPanBase"}, {"source": "PizzaBase", "target": "ThinAndCrispyBase"}, {"source": "PizzaTopping", "target": "FishTopping"}, {"source": "PizzaTopping", "target": "VegetableTopping"}, {"source": "PizzaTopping", "target": "HerbSpiceTopping"}, {"source": "PizzaTopping", "target": "CheeseTopping"}, {"source": "PizzaTopping", "target": "MeatTopping"}, {"source": "PizzaTopping", "target": "FruitTopping"}, {"source": "PizzaTopping", "target": "NutTopping"}, {"source": "PizzaTopping", "target": "SauceTopping"}, {"source": "FishTopping", "target": "AnchoviesTopping"}, {"source": "FishTopping", "target": "PrawnsTopping"}, {"source": "FishTopping", "target": "MixedSeafoodTopping"}, {"source": "VegetableTopping", "target": "TomatoTopping"}, {"source": "VegetableTopping", "target": "ArtichokeTopping"}, {"source": "VegetableTopping", "target": "AsparagusTopping"}, {"source": "VegetableTopping", "target": "OnionTopping"}, {"source": "VegetableTopping", "target": "CaperTopping"}, {"source": "VegetableTopping", "target": "OliveTopping"}, {"source": "VegetableTopping", "target": "CheeseyVegetableTopping"}, {"source": "VegetableTopping", "target": "GarlicTopping"}, {"source": "VegetableTopping", "target": "SpinachTopping"}, {"source": "VegetableTopping", "target": "MushroomTopping"}, {"source": "VegetableTopping", "target": "LeekTopping"}, {"source": "VegetableTopping", "target": "PetitPoisTopping"}, {"source": "VegetableTopping", "target": "PepperTopping"}, {"source": "VegetableTopping", "target": "RocketTopping"}, {"source": "TomatoTopping", "target": "SundriedTomatoTopping"}, {"source": "TomatoTopping", "target": "SlicedTomatoTopping"}, {"source": "OnionTopping", "target": "RedOnionTopping"}, {"source": "PepperTopping", "target": "JalapenoPepperTopping"}, {"source": "PepperTopping", "target": "PeperonataTopping"}, {"source": "PepperTopping", "target": "GreenPepperTopping"}, {"source": "PepperTopping", "target": "SweetPepperTopping"}, {"source": "GreenPepperTopping", "target": "HotGreenPepperTopping"}, {"source": "HerbSpiceTopping", "target": "CajunSpiceTopping"}, {"source": "HerbSpiceTopping", "target": "RosemaryTopping"}, {"source": "CheeseTopping", "target": "MozzarellaTopping"}, {"source": "CheeseTopping", "target": "GoatsCheeseTopping"}, {"source": "CheeseTopping", "target": "ParmesanTopping"}, {"source": "CheeseTopping", "target": "FourCheesesTopping"}, {"source": "CheeseTopping", "target": "GorgonzolaTopping"}, {"source": "MeatTopping", "target": "PeperoniSausageTopping"}, {"source": "MeatTopping", "target": "HamTopping"}, {"source": "MeatTopping", "target": "ChickenTopping"}, {"source": "MeatTopping", "target": "HotSpicedBeefTopping"}, {"source": "HamTopping", "target": "ParmaHamTopping"}, {"source": "FruitTopping", "target": "SultanaTopping"}, {"source": "NutTopping", "target": "PineKernels"}, {"source": "SauceTopping", "target": "TobascoPepperSauce"}, {"source": "ValuePartition", "target": "Spiciness"}, {"source": "Spiciness", "target": "Mild"}, {"source": "Spiciness", "target": "Hot"}, {"source": "Spiciness", "target": "Medium"}]}